runreg/__init__.py
runreg/client.py
runreg/utils.py
runregistryclient-0.3.0.dist-info/LICENSE
runregistryclient-0.3.0.dist-info/METADATA
runregistryclient-0.3.0.dist-info/WHEEL
runregistryclient-0.3.0.dist-info/top_level.txt
runregistryclient-0.3.0.dist-info/RECORD
