Metadata-Version: 2.1
Name: runregistryclient
Version: 0.3.0
Summary: UNKNOWN
Home-page: https://github.com/ptrstn/runregistryclient
Author: Peter Stein
Author-email: peter.stein@cern.ch
License: UNKNOWN
Platform: UNKNOWN
Classifier: License :: OSI Approved :: GNU General Public License v3 (GPLv3)
Requires-Dist: requests
Requires-Dist: cernrequests
